{"nodes": [{"id": "notebooklmmodulecard", "label": "NotebookLMModuleCard.tsx", "file_type": "code", "source_file": "src/components/NotebookLMModuleCard.tsx", "source_location": "L1"}, {"id": "notebooklmmodulecard_buildcommandhint", "label": "buildCommandHint()", "file_type": "code", "source_file": "src/components/NotebookLMModuleCard.tsx", "source_location": "L8"}, {"id": "notebooklmmodulecard_notebooklmmodulecard", "label": "NotebookLMModuleCard()", "file_type": "code", "source_file": "src/components/NotebookLMModuleCard.tsx", "source_location": "L11"}], "edges": [{"source": "notebooklmmodulecard", "target": "notebooklm_context", "relation": "imports_from", "confidence": "EXTRACTED", "source_file": "src/components/NotebookLMModuleCard.tsx", "source_location": "L1", "weight": 1.0}, {"source": "notebooklmmodulecard", "target": "notebooklmmodulecard_buildcommandhint", "relation": "contains", "confidence": "EXTRACTED", "source_file": "src/components/NotebookLMModuleCard.tsx", "source_location": "L8", "weight": 1.0}, {"source": "notebooklmmodulecard", "target": "notebooklmmodulecard_notebooklmmodulecard", "relation": "contains", "confidence": "EXTRACTED", "source_file": "src/components/NotebookLMModuleCard.tsx", "source_location": "L11", "weight": 1.0}]}